Metadata-Version: 2.4
Name: llama-index-vector-stores-azurecosmosmongo
Version: 0.7.0
Summary: llama-index vector_stores azurecosmosmongo integration
Author-email: Aayush Kataria <aayushkataria3011@gmail.com>
License-Expression: MIT
License-File: LICENSE
Requires-Python: <4.0,>=3.9
Requires-Dist: llama-index-core<0.14,>=0.13.0
Requires-Dist: pymongo<5,>=4.6.1
